wikipedia_histories/__init__.py
wikipedia_histories/get_histories.py
wikipedia_histories/retrieve_metadata.py
wikipedia_histories/revision.py
wikipedia_histories/networks/__init__.py
wikipedia_histories/networks/analyze_networks.py
wikipedia_histories/networks/get_category_articles.py
wikipedia_histories/networks/network_builder.py
wikipedia_histories-1.1.0.dist-info/LICENSE
wikipedia_histories-1.1.0.dist-info/METADATA
wikipedia_histories-1.1.0.dist-info/WHEEL
wikipedia_histories-1.1.0.dist-info/top_level.txt
wikipedia_histories-1.1.0.dist-info/RECORD
