Metadata-Version: 2.1
Name: wikipedia-histories
Version: 1.1.0
Summary: A Python tool to pull the complete edit history of a Wikipedia page
Home-page: https://github.com/ndrezn/wikipedia-histories
Author: Nathan Drezner
Author-email: nathan@drezner.xyz
Classifier: Programming Language :: Python :: 3
Classifier: License :: OSI Approved :: MIT License
Classifier: Operating System :: OS Independent
Requires-Python: >=3.6
License-File: LICENSE
Requires-Dist: aiohttp (>=3.8.0)
Requires-Dist: lxml (==4.9.1)
Requires-Dist: mwclient (==0.10.1)
Requires-Dist: mwparserfromhell (==0.6)
Requires-Dist: pandas (>=1.2.3)
Requires-Dist: wikipedia-api (==0.5.4)
Provides-Extra: networks
Requires-Dist: networkx (>=2.6) ; extra == 'networks'
Requires-Dist: python-igraph (==0.9.1) ; extra == 'networks'
